[
    {
        "key": "ctrl+shift+f",
        "command": "workbench.action.findInFiles"
    },
    {
        "key": "shift+cmd+f",
        "command": "editor.action.format"
    },
    {
        "key": "ctrl+a",
        "command": "cursorLineStart",
        "when": "editorTextFocus"
    },
    {
        "key": "ctrl+e",
        "command": "cursorLineEnd",
        "when": "editorTextFocus"
    },
    {
        "key": "ctrl+x",
        "command": "editor.action.clipboardCutAction",
        "when": "editorTextFocus"
    },
    {
        "key": "alt+]",
        "command": "editor.action.commentLine",
        "when": "editorTextFocus"
    },
    {
        "key": "alt+]",
        "command": "editor.action.commentLine",
        "when": "editorTextFocus"
    },
    {
        "key": "ctrl+x 3",
        "command": "workbench.action.splitEditorRight"
    },
    {
        "key": "ctrl+x",
        "command": "editor.action.clipboardCutAction",
        "when": "editorTextFocus"
    },
    {
        "key": "ctrl+shift+a",
        "command": "editor.action.selectAll",
        "when": "editorTextFocus"
    },
    {
        "key": "shift+alt+f",
        "command": "editor.action.format",
        "when": "editorTextFocus"
    },
    {
        "key": "alt+]",
        "command": "editor.action.commentLine",
        "when": "editorTextFocus"
    },
    {
        "key": "tab",
        "command": "editor.action.indentLines",
        "when": "editorTextFocus"
    },
    {
        "key": "shift+tab",
        "command": "editor.action.outdentLines",
        "when": "editorTextFocus"
    }
]